{"views":{"cms":{"groupKey":"content_view","onboardingKey":"free_cms","dismissedExploreCards":null,"newContent":null,"viewed":null},"service":{"groupKey":"service_free_view","onboardingKey":"free_service","dismissedExploreCards":null,"newContent":null,"viewed":null},"marketing":{"groupKey":"marketing_free_view","onboardingKey":"free_marketing","dismissedExploreCards":null,"newContent":null,"viewed":null},"sales":{"groupKey":"sales_free_view","onboardingKey":"free_sales","dismissedExploreCards":null,"newContent":null,"viewed":null}},"selectedView":"sales","viewed":null,"preUserGuideGroupKey":null,"enrolledInUserGuide":null,"businessBoxId":null,"useCaseOption":null,"crmTemplate":null,"isAccountCreator":null}